[{"exist":false,"normal":false,"url":false},{"exist":false,"normal":false,"url":false},{"exist":false,"normal":false,"url":false},{"exist":false,"normal":false,"url":false},{"exist":false,"normal":false,"url":false},{"exist":false,"normal":false,"url":false},{"exist":false,"normal":false,"url":false},{"exist":false,"normal":false,"url":false},{"exist":false,"normal":false,"url":false},{"exist":false,"normal":false,"url":false},{"exist":false,"normal":false,"url":false},{"exist":false,"normal":false,"url":false},{"exist":false,"normal":false,"url":false},{"exist":false,"normal":false,"url":false},{"exist":false,"normal":false,"url":false},{"exist":false,"normal":false,"url":false},{"exist":true,"normal":true,"url":"https://webcat-1255822810.cos.ap-guangzhou.myqcloud.com/file/2024-04-06/10/31161875166533-92380-PUBG.zip"},{"exist":false,"normal":false,"url":false},{"exist":false,"normal":false,"url":false},{"exist":false,"normal":false,"url":false},{"exist":false,"normal":false,"url":false},{"exist":false,"normal":false,"url":false},{"exist":false,"normal":false,"url":false},{"exist":false,"normal":false,"url":false},{"exist":false,"normal":false,"url":false},{"exist":false,"normal":false,"url":false},{"exist":false,"normal":false,"url":false},{"exist":false,"normal":false,"url":false},{"exist":false,"normal":false,"url":false},{"exist":false,"normal":false,"url":false},{"exist":false,"normal":false,"url":false},{"exist":false,"normal":false,"url":false},{"exist":false,"normal":false,"url":false},{"exist":false,"normal":false,"url":false},{"exist":false,"normal":false,"url":false},{"exist":false,"normal":false,"url":false},{"exist":false,"normal":false,"url":false},{"exist":false,"normal":false,"url":false},{"exist":false,"normal":false,"url":false},{"exist":false,"normal":false,"url":false},{"exist":false,"normal":false,"url":false},{"exist":false,"normal":false,"url":false},{"exist":false,"normal":false,"url":false},{"exist":false,"normal":false,"url":false},{"exist":false,"normal":false,"url":false},{"exist":false,"normal":false,"url":false},{"exist":false,"normal":false,"url":false},{"exist":false,"normal":false,"url":false},{"exist":false,"normal":false,"url":false},{"exist":false,"normal":false,"url":false},{"exist":false,"normal":false,"url":false},{"exist":false,"normal":false,"url":false},{"exist":false,"normal":false,"url":false},{"exist":false,"normal":false,"url":false},{"exist":false,"normal":false,"url":false},{"exist":false,"normal":false,"url":false},{"exist":false,"normal":false,"url":false},{"exist":false,"normal":false,"url":false},{"exist":false,"normal":false,"url":false},{"exist":false,"normal":false,"url":false},{"exist":false,"normal":false,"url":false},{"exist":false,"normal":false,"url":false},{"exist":false,"normal":false,"url":false},{"exist":false,"normal":false,"url":false},{"exist":false,"normal":false,"url":false},{"exist":false,"normal":false,"url":false},{"exist":false,"normal":false,"url":false},{"exist":false,"normal":false,"url":false},{"exist":false,"normal":false,"url":false},{"exist":false,"normal":false,"url":false},{"exist":false,"normal":false,"url":false},{"exist":false,"normal":false,"url":false},{"exist":false,"normal":false,"url":false},{"exist":false,"normal":false,"url":false},{"exist":false,"normal":false,"url":false},{"exist":false,"normal":false,"url":false},{"exist":false,"normal":false,"url":false},{"exist":false,"normal":false,"url":false},{"exist":false,"normal":false,"url":false},{"exist":false,"normal":false,"url":false},{"exist":false,"normal":false,"url":false},{"exist":false,"normal":false,"url":false},{"exist":false,"normal":false,"url":false},{"exist":false,"normal":false,"url":false},{"exist":false,"normal":false,"url":false},{"exist":false,"normal":false,"url":false},{"exist":false,"normal":false,"url":false},{"exist":false,"normal":false,"url":false},{"exist":false,"normal":false,"url":false},{"exist":false,"normal":false,"url":false},{"exist":false,"normal":false,"url":false},{"exist":false,"normal":false,"url":false},{"exist":false,"normal":false,"url":false},{"exist":false,"normal":false,"url":false},{"exist":false,"normal":false,"url":false},{"exist":false,"normal":false,"url":false},{"exist":false,"normal":false,"url":false},{"exist":false,"normal":false,"url":false},{"exist":false,"normal":false,"url":false},{"exist":false,"normal":false,"url":false}]